freemobsms/COPYING
freemobsms/__init__.py
freemobsms/freemobsms.py
freemobsms/setup.py
freemobsms-1.0.3.data/scripts/freemobsms
freemobsms-1.0.3.dist-info/METADATA
freemobsms-1.0.3.dist-info/WHEEL
freemobsms-1.0.3.dist-info/top_level.txt
freemobsms-1.0.3.dist-info/RECORD
