Metadata-Version: 2.1
Name: freemobsms
Version: 1.0.3
Summary: Free mobile SMS notifier.
Home-page: UNKNOWN
Author: h2d
Author-email: h2d2021@protonmail.com
License: GNU Affero General Public License
Platform: UNKNOWN
Classifier: License :: OSI Approved :: GNU Affero General Public License v3
Requires-Dist: requests
